package/__init__.py
package/main.py
randomstuffbro-1.0.0.dist-info/METADATA
randomstuffbro-1.0.0.dist-info/WHEEL
randomstuffbro-1.0.0.dist-info/top_level.txt
randomstuffbro-1.0.0.dist-info/RECORD
